letterbomb_web/__init__.py
letterbomb_web/__main__.py
letterbomb_web/config.toml
letterbomb_web/static/letterbomb.png
letterbomb_web/static/static.css
letterbomb_web/static/web.js
letterbomb_web/static/sublinks/pypi.svg
letterbomb_web/static/sublinks/readthedocs.svg
letterbomb_web/static/sublinks/wiibrew.svg
letterbomb_web/templates/index.html
letterbomb_web-1.1.dist-info/LICENSE.txt
letterbomb_web-1.1.dist-info/METADATA
letterbomb_web-1.1.dist-info/WHEEL
letterbomb_web-1.1.dist-info/top_level.txt
letterbomb_web-1.1.dist-info/RECORD
