Metadata-Version: 2.1
Name: letterbomb-web
Version: 1.1
Summary: A flask module that complements the letterbomb API.
Author: WhoAteMyButter
License: MIT
Project-URL: Documentation, https://letterbomb.readthedocs.io/en/latest/web.html
Project-URL: Source, https://gitlab.com/whoatemybutter/letterbomb_web
Project-URL: Changelog, https://gitlab.com/whoatemybutter/letterbomb_web/-/blob/master/CHANGELOG.md
Keywords: letterbomb,letter bomb,wii,failoverflow,fail0verflow,fail overflow,fail 0verflow,exploit,wii hack,letterbomb web,letterbomb flask
Classifier: Operating System :: OS Independent
Classifier: Development Status :: 5 - Production/Stable
Classifier: Programming Language :: Python :: 3 :: Only
Classifier: Programming Language :: Python :: 3.10
Classifier: Programming Language :: Python :: 3.11
Classifier: License :: OSI Approved :: MIT License
Classifier: Topic :: Games/Entertainment
Classifier: Framework :: Flask
Requires-Python: >=3.10
License-File: LICENSE.txt
Requires-Dist: letterbomb ~=4.0
